taskd/__init__.py
taskd/main.py
taskd-0.0.0.1.dist-info/METADATA
taskd-0.0.0.1.dist-info/WHEEL
taskd-0.0.0.1.dist-info/licenses/LICENSE
taskd-0.0.0.1.dist-info/RECORD
