Metadata-Version: 2.4
Name: taskd
Version: 0.0.0.1
Summary: A Python interface for TaskC and TaskD project
Project-URL: Homepage, https://github.com/L-F-Z/TaskC
Project-URL: Issues, https://github.com/L-F-Z/TaskC/issues
Author-email: Fengzhi Li <lfzbbaa@163.com>
License-Expression: Apache-2.0
License-File: LICENSE
Classifier: Operating System :: OS Independent
Classifier: Programming Language :: Python :: 3
Requires-Python: >=3.8
